olmen_api.py
olmen_api-0.0.1.dist-info/LICENSE
olmen_api-0.0.1.dist-info/METADATA
olmen_api-0.0.1.dist-info/WHEEL
olmen_api-0.0.1.dist-info/top_level.txt
olmen_api-0.0.1.dist-info/RECORD
